Metadata-Version: 2.1
Name: py-ztj-aria2client
Version: 0.0.1
Summary: python aria2client package
Home-page: http://github.com/ztj1993/PythonPackages/blob/master/py_aria2rpc
Author: ZhangTianJie
Author-email: ztj1993@gmail.com
License: MIT License
Keywords: aria2 client rpc start stop service
Platform: UNKNOWN
Requires-Dist: py-ztj-aria2local
Requires-Dist: py-ztj-aria2rpc
